testbase
