Metadata-Version: 1.1
Name: django-testing-base
Version: 0.4.0
Summary: Simple Django testing base classes and patterns
Home-page: https://github.com/tctimmeh/django-testing-base
Author: Tim Court
Author-email: tctimmeh@gmail.com
License: MIT License
Platform: UNKNOWN
Classifier: Development Status :: 3 - Alpha
Classifier: Environment :: Web Environment
Classifier: Framework :: Django
Classifier: Intended Audience :: Developers
Classifier: License :: OSI Approved :: MIT License
Classifier: Operating System :: OS Independent
Classifier: Programming Language :: Python
Classifier: Programming Language :: Python :: 3
Classifier: Programming Language :: Python :: 3.3
Classifier: Programming Language :: Python :: 3.4
